MANIFEST.in
README.rst
setup.py
aliyun_python_sdk_mopen.egg-info/PKG-INFO
aliyun_python_sdk_mopen.egg-info/SOURCES.txt
aliyun_python_sdk_mopen.egg-info/dependency_links.txt
aliyun_python_sdk_mopen.egg-info/requires.txt
aliyun_python_sdk_mopen.egg-info/top_level.txt
aliyunsdkmopen/__init__.py
aliyunsdkmopen/request/__init__.py
aliyunsdkmopen/request/v20180211/MoPenAddGroupMemberRequest.py
aliyunsdkmopen/request/v20180211/MoPenBindIsvRequest.py
aliyunsdkmopen/request/v20180211/MoPenCreateDeviceRequest.py
aliyunsdkmopen/request/v20180211/MoPenDeleteGroupMemberRequest.py
aliyunsdkmopen/request/v20180211/MoPenDeleteGroupRequest.py
aliyunsdkmopen/request/v20180211/MoPenDoRecognizeRequest.py
aliyunsdkmopen/request/v20180211/MoPenFindGroupRequest.py
aliyunsdkmopen/request/v20180211/MoPenQueryCanvasRequest.py
aliyunsdkmopen/request/v20180211/MoPenSendMqttMessageRequest.py
aliyunsdkmopen/request/v20180211/MopenCreateGroupRequest.py
aliyunsdkmopen/request/v20180211/__init__.py